[
  {
    "id": 1,
    "image": "https://i.imgur.com/P2CRqG5.png"
  },
  {
    "id": 2,
    "image": "https://i.imgur.com/ZZ08twX.png"
  },
  {
    "id": 3,
    "image": "https://i.imgur.com/GNZOu3w.png"
  },
  {
    "id": 4,
    "image": "https://i.imgur.com/IPFyVdq.png"
  },
  {
    "id": 5,
    "image": "https://i.imgur.com/dPDL5n1.png"
  },
  {
    "id": 6,
    "image": "https://i.imgur.com/P7WEjHY.png"
  },
  {
    "id": 7,
    "image": "https://i.imgur.com/049AJ7x.png"
  },
  {
    "id": 8,
    "image": "https://i.imgur.com/lu2SKzQ.png"
  },
  {
    "id": 9,
    "image": "https://i.imgur.com/rWGtwBZ.png"
  },
  {
    "id": 10,
    "image": "https://i.imgur.com/7K1dtg6.png"
  },
  {
    "id": 11,
    "image": "https://i.imgur.com/qHrMTf1.png"
  },
  {
    "id": 12,
    "image": "https://i.imgur.com/dc9JnMW.png"
  }
]
